odoo/addons/web_widget_dropdown_dynamic/README.rst
odoo/addons/web_widget_dropdown_dynamic/__init__.py
odoo/addons/web_widget_dropdown_dynamic/__manifest__.py
odoo/addons/web_widget_dropdown_dynamic/demo/ir_filters_view.xml
odoo/addons/web_widget_dropdown_dynamic/demo/ir_model_fields.xml
odoo/addons/web_widget_dropdown_dynamic/i18n/de.po
odoo/addons/web_widget_dropdown_dynamic/i18n/es.po
odoo/addons/web_widget_dropdown_dynamic/i18n/it.po
odoo/addons/web_widget_dropdown_dynamic/i18n/tr.po
odoo/addons/web_widget_dropdown_dynamic/i18n/web_widget_dropdown_dynamic.pot
odoo/addons/web_widget_dropdown_dynamic/models/__init__.py
odoo/addons/web_widget_dropdown_dynamic/models/ir_filters.py
odoo/addons/web_widget_dropdown_dynamic/readme/CONTRIBUTORS.md
odoo/addons/web_widget_dropdown_dynamic/readme/CREDITS.md
odoo/addons/web_widget_dropdown_dynamic/readme/DESCRIPTION.md
odoo/addons/web_widget_dropdown_dynamic/readme/USAGE.md
odoo/addons/web_widget_dropdown_dynamic/static/description/icon.png
odoo/addons/web_widget_dropdown_dynamic/static/description/index.html
odoo/addons/web_widget_dropdown_dynamic/static/src/js/field_dynamic_dropdown.esm.js
odoo/addons/web_widget_dropdown_dynamic/static/tests/web_widget_dropdown_dynamic_tests.esm.js
odoo_addon_web_widget_dropdown_dynamic-18.0.2.0.0.2.dist-info/METADATA
odoo_addon_web_widget_dropdown_dynamic-18.0.2.0.0.2.dist-info/WHEEL
odoo_addon_web_widget_dropdown_dynamic-18.0.2.0.0.2.dist-info/top_level.txt
odoo_addon_web_widget_dropdown_dynamic-18.0.2.0.0.2.dist-info/RECORD
