Metadata-Version: 2.1
Name: odoo-addon-web_widget_dropdown_dynamic
Version: 18.0.2.0.0.2
Requires-Python: >=3.10
Requires-Dist: odoo==18.0.*
Summary: This module adds support for dynamic dropdown widget
Home-page: https://github.com/OCA/web
License: LGPL-3
Author: CorporateHub, Odoo Community Association (OCA)
Author-email: support@odoo-community.org
Classifier: Programming Language :: Python
Classifier: Framework :: Odoo
Classifier: Framework :: Odoo :: 18.0
Classifier: License :: OSI Approved :: GNU Lesser General Public License v3 (LGPLv3)
